MANIFEST.in
README.md
setup.py
XpongeLib/__init__.py
XpongeLib/main.c
XpongeLib.egg-info/PKG-INFO
XpongeLib.egg-info/SOURCES.txt
XpongeLib.egg-info/dependency_links.txt
XpongeLib.egg-info/top_level.txt
XpongeLib/parmchk_mod/CONNECT.TPL
XpongeLib/parmchk_mod/PARMCHK.DAT
XpongeLib/parmchk_mod/PARM_BLBA_GAFF.DAT
XpongeLib/parmchk_mod/PARM_BLBA_GAFF2.DAT
XpongeLib/parmchk_mod/__init__.py
XpongeLib/parmchk_mod/ac.c
XpongeLib/parmchk_mod/atom.h
XpongeLib/parmchk_mod/common.c
XpongeLib/parmchk_mod/common.h
XpongeLib/parmchk_mod/define.h
XpongeLib/parmchk_mod/eprintf.c
XpongeLib/parmchk_mod/eprintf.h
XpongeLib/parmchk_mod/gaff.dat
XpongeLib/parmchk_mod/gaff2.dat
XpongeLib/parmchk_mod/mol2.c
XpongeLib/parmchk_mod/parmchk2.c
XpongeLib/parmchk_mod/prep.c
XpongeLib/parmchk_mod/rotate.c
XpongeLib/parmchk_mod/utility.c