Metadata-Version: 1.0
Name: XpongeLib
Version: 0.0.8.9
Summary: the C++ Lib for the package for building molecular dynamics inputs for SPONGE
Home-page: https://gitee.com/gao_hyp_xyj_admin/xponge
Author: Yijie Xia
Author-email: yijiexia@pku.edu.cn
License: UNKNOWN
Platform: UNKNOWN
